pdpexplorer/__init__.py
pdpexplorer/_frontend.py
pdpexplorer/_version.py
pdpexplorer/logging.py
pdpexplorer/metadata.py
pdpexplorer/pdp.py
pdpexplorer/pdpexplorer.py
pdpexplorer/plotting.py
pdpexplorer/ticks.py
pdpexplorer/tqdm_joblib.py
pdpexplorer/widget.py
pdpexplorer/labextension/build_log.json
pdpexplorer/labextension/package.json
pdpexplorer/labextension/static/568.a64f0f370c40da1e28c8.js
pdpexplorer/labextension/static/568.b67af1c4d6419b1edb9c.js
pdpexplorer/labextension/static/568.b97482293a512c1e8dec.js
pdpexplorer/labextension/static/568.e4fcc77c5a74a5746985.js
pdpexplorer/labextension/static/568.fd9861525298175d4945.js
pdpexplorer/labextension/static/713.bdb6a847553ba6f697b8.js
pdpexplorer/labextension/static/713.bdb6a847553ba6f697b8.js.LICENSE.txt
pdpexplorer/labextension/static/lib_index_js.8ad3e3483bc69cfd419f.js
pdpexplorer/labextension/static/lib_index_js.8ad3e3483bc69cfd419f.js.map
pdpexplorer/labextension/static/remoteEntry.25020cf6cddb97bbe535.js
pdpexplorer/labextension/static/remoteEntry.6bf70591202890b0341e.js
pdpexplorer/labextension/static/remoteEntry.7c46547f4528c528f0e2.js
pdpexplorer/labextension/static/remoteEntry.7c46547f4528c528f0e2.js.map
pdpexplorer/labextension/static/remoteEntry.bfb65fcfeae1fed0c06d.js
pdpexplorer/labextension/static/remoteEntry.c41091b80275a525355b.js
pdpexplorer/labextension/static/remoteEntry.e8050a5ed300d5e5b074.js
pdpexplorer/labextension/static/style.js
pdpexplorer/labextension/static/third-party-licenses.json
pdpexplorer/labextension/static/vendors-node_modules_jupyter-widgets_base_lib_index_js.ff879425c5e7003d47f4.js
pdpexplorer/labextension/static/vendors-node_modules_jupyter-widgets_base_lib_index_js.ff879425c5e7003d47f4.js.map
pdpexplorer/nbextension/extension.js
pdpexplorer/nbextension/index.js
pdpexplorer-0.3.2.data/data/etc/jupyter/nbconfig/notebook.d/pdpexplorer.json
pdpexplorer-0.3.2.data/data/share/jupyter/labextensions/pdp-explorer/install.json
pdpexplorer-0.3.2.dist-info/LICENSE.txt
pdpexplorer-0.3.2.dist-info/METADATA
pdpexplorer-0.3.2.dist-info/WHEEL
pdpexplorer-0.3.2.dist-info/top_level.txt
pdpexplorer-0.3.2.dist-info/RECORD
