Metadata-Version: 2.1
Name: pdpexplorer
Version: 0.3.2
Summary: A Jupyter widget for exploring partial dependence plots.
Home-page: https://github.com/nyuvis/pdp-explorer
Author: Daniel Kerrigan
Author-email: kerrigan.d@northeastern.edu
License: BSD
Keywords: Jupyter,Widgets,IPython
Platform: Linux
Platform: Mac OS X
Platform: Windows
Classifier: Intended Audience :: Developers
Classifier: Intended Audience :: Science/Research
Classifier: License :: OSI Approved :: BSD License
Classifier: Programming Language :: Python
Classifier: Programming Language :: Python :: 3
Classifier: Programming Language :: Python :: 3.4
Classifier: Programming Language :: Python :: 3.5
Classifier: Programming Language :: Python :: 3.6
Classifier: Programming Language :: Python :: 3.7
Classifier: Framework :: Jupyter
Requires-Python: >=3.7.1
License-File: LICENSE.txt
Requires-Dist: ipywidgets (<9,>=7.6.0)
Requires-Dist: pandas (>=1.3.5)
Requires-Dist: numpy (>=1.21.5)
Requires-Dist: joblib (>=1.1.0)
Requires-Dist: scikit-learn (>=1.0.2)
Requires-Dist: tqdm (>=4.64.1)
Requires-Dist: tslearn (>=0.5.3)
Requires-Dist: h5py
Provides-Extra: dev
Requires-Dist: pylint ; extra == 'dev'
Requires-Dist: black ; extra == 'dev'
Requires-Dist: twine ; extra == 'dev'
Requires-Dist: jupyter-packaging ; extra == 'dev'
Provides-Extra: docs
Requires-Dist: jupyter-sphinx ; extra == 'docs'
Requires-Dist: nbsphinx ; extra == 'docs'
Requires-Dist: nbsphinx-link ; extra == 'docs'
Requires-Dist: pytest-check-links ; extra == 'docs'
Requires-Dist: pypandoc ; extra == 'docs'
Requires-Dist: recommonmark ; extra == 'docs'
Requires-Dist: sphinx (>=1.5) ; extra == 'docs'
Requires-Dist: furo ; extra == 'docs'
Provides-Extra: examples
Requires-Dist: pmlb ; extra == 'examples'
Requires-Dist: xgboost ; extra == 'examples'
Provides-Extra: test
Requires-Dist: pytest ; extra == 'test'
